Workbook

Sheet README
B2: REAL ESTATE PORTFOLIO HUB
B3: Single-source workbook for tracking properties, maintenance, expenses, refinance opportunities, and Ohio acquisitions.
B5: HOW TO USE
B7: Sheet | C7: Purpose
B8: 1. Properties | C8: Master list of every property you own. Fill blue input columns; black formula columns calculate equity, LTV, monthly cash flow, and refi flag.
B9: 2. Maintenance | C9: Log inspections, repairs, system ages. Status column auto-flags items overdue or due within 60 days.
B10: 3. Expenses | C10: Day-to-day expense log. Enter date, property, category, amount. Pivot-style monthly summary at right auto-totals by property.
B11: 4. Refinance | C11: Per-property refi analyzer: current rate vs. market rate, monthly savings, break-even months, decision flag.
B12: 5. Ohio Prospects | C12: Pipeline of properties you're evaluating. Built-in scoring: cap rate, cash-on-cash, 1% rule, score out of 100.
B13: 6. Ohio Market | C13: Reference research on top Ohio cities, median prices, cap rate benchmarks, and current refi rates.
B14: 7. Settings | C14: Global assumptions (current market mortgage rate, refi closing cost %, target cap rate). Change once and the whole workbook updates.
B17: COLOR LEGEND
B19: Blue text | C19: User input — change these
B20: Black text | C20: Formulas — do not overwrite
B21: Green text | C21: Cross-sheet links
B22: Yellow fill | C22: Key assumption to review
B23: Red fill | C23: Alert / action needed
B24: Amber fill | C24: Caution / due soon
B25: Green fill | C25: OK / on track
B27: Built May 2026 · Update Settings sheet whenever market rates move.

Sheet Properties
A1: PROPERTY MASTER LIST
A3: ID | B3: Nickname | C3: Address | D3: City | E3: State | F3: Type | G3: Year Built | H3: Bed/Bath | I3: Purchase Date | J3: Purchase Price | K3: Current Est. Value | L3: Mortgage Balance | M3: Equity | N3: LTV % | O3: Loan Rate % | P3: Loan Term (yrs) | Q3: Monthly P&I | R3: Monthly Tax+Ins | S3: Monthly HOA | T3: Monthly Rent | U3: Effective Rent | V3: Monthly Op Exp | W3: Mgmt Fee | X3: Net Cash Flow | Y3: Annual NOI | Z3: Cap Rate | AA3: Refi Flag | AB3: Notes
A4: 1 | B4: Sample 1 | C4: 123 Maple St | D4: Columbus | E4: OH | F4: SFR | G4: 1998 | H4: 3/2 | I4: 2021-06-15 | J4: 185000 | K4: 235000 | L4: 142000 | M4: =K4-L4 -> 93000 | N4: =IFERROR(L4/K4,0) -> 0.60425532 | O4: 0.0625 | P4: 30 | Q4: 1135 | R4: 425 | S4: 0 | T4: 1850 | U4: =T4*(1-VacancyPct) -> 1702 | V4: 0 | W4: =T4*MgmtPct -> 148 | X4: =U4-Q4-R4-S4-V4-W4 -> -6 | Y4: =(U4-R4-S4-V4-W4)*12 -> 13548 | Z4: =IFERROR(Y4/K4,0) -> 0.057651064 | AA4: =IF(O4="","",IF(AND(O4-MarketRate30>=0.005,(1-N4)>=MinEquityPct),"Consider Refi",IF(O4-MarketRate30<0.005,"Rate already low","Build equity first"))) -> Rate already low | AB4: 250
A5: 2 | B5: Sample 2 | C5: 456 Oak Ave | D5: Cleveland | E5: OH | F5: SFR | G5: 1965 | H5: 4/2 | I5: 2019-03-01 | J5: 110000 | K5: 165000 | L5: 78000 | M5: =K5-L5 -> 87000 | N5: =IFERROR(L5/K5,0) -> 0.47272727 | O5: 0.0425 | P5: 30 | Q5: 525 | R5: 320 | S5: 0 | T5: 1450 | U5: =T5*(1-VacancyPct) -> 1334 | V5: 0 | W5: =T5*MgmtPct -> 116 | X5: =U5-Q5-R5-S5-V5-W5 -> 373 | Y5: =(U5-R5-S5-V5-W5)*12 -> 10776 | Z5: =IFERROR(Y5/K5,0) -> 0.065309091 | AA5: =IF(O5="","",IF(AND(O5-MarketRate30>=0.005,(1-N5)>=MinEquityPct),"Consider Refi",IF(O5-MarketRate30<0.005,"Rate already low","Build equity first"))) -> Rate already low | AB5: 180
A6: 3 | B6: Sample 3 | C6: 789 Pine Ln | D6: Cincinnati | E6: OH | F6: Duplex | G6: 1978 | H6: 2x2/1 | I6: 2023-09-10 | J6: 240000 | K6: 275000 | L6: 205000 | M6: =K6-L6 -> 70000 | N6: =IFERROR(L6/K6,0) -> 0.74545455 | O6: 0.075 | P6: 30 | Q6: 1430 | R6: 510 | S6: 0 | T6: 2400 | U6: =T6*(1-VacancyPct) -> 2208 | V6: 0 | W6: =T6*MgmtPct -> 192 | X6: =U6-Q6-R6-S6-V6-W6 -> 76 | Y6: =(U6-R6-S6-V6-W6)*12 -> 18072 | Z6: =IFERROR(Y6/K6,0) -> 0.065716364 | AA6: =IF(O6="","",IF(AND(O6-MarketRate30>=0.005,(1-N6)>=MinEquityPct),"Consider Refi",IF(O6-MarketRate30<0.005,"Rate already low","Build equity first"))) -> Consider Refi | AB6: 320
A7: 4 | M7: =IF(K7="","",K7-L7) | N7: =IFERROR(L7/K7,"") | U7: =IF(T7="","",T7*(1-VacancyPct)) | W7: =IF(T7="","",T7*MgmtPct) | X7: =IF(T7="","",U7-Q7-R7-S7-V7-W7) | Y7: =IF(T7="","",(U7-R7-S7-V7-W7)*12) | Z7: =IFERROR(Y7/K7,"") | AA7: =IF(O7="","",IF(AND(O7-MarketRate30>=0.005,(1-N7)>=MinEquityPct),"Consider Refi",IF(O7-MarketRate30<0.005,"Rate already low","Build equity first")))
A8: 5 | M8: =IF(K8="","",K8-L8) | N8: =IFERROR(L8/K8,"") | U8: =IF(T8="","",T8*(1-VacancyPct)) | W8: =IF(T8="","",T8*MgmtPct) | X8: =IF(T8="","",U8-Q8-R8-S8-V8-W8) | Y8: =IF(T8="","",(U8-R8-S8-V8-W8)*12) | Z8: =IFERROR(Y8/K8,"") | AA8: =IF(O8="","",IF(AND(O8-MarketRate30>=0.005,(1-N8)>=MinEquityPct),"Consider Refi",IF(O8-MarketRate30<0.005,"Rate already low","Build equity first")))
A9: 6 | M9: =IF(K9="","",K9-L9) | N9: =IFERROR(L9/K9,"") | U9: =IF(T9="","",T9*(1-VacancyPct)) | W9: =IF(T9="","",T9*MgmtPct) | X9: =IF(T9="","",U9-Q9-R9-S9-V9-W9) | Y9: =IF(T9="","",(U9-R9-S9-V9-W9)*12) | Z9: =IFERROR(Y9/K9,"") | AA9: =IF(O9="","",IF(AND(O9-MarketRate30>=0.005,(1-N9)>=MinEquityPct),"Consider Refi",IF(O9-MarketRate30<0.005,"Rate already low","Build equity first")))
A10: 7 | M10: =IF(K10="","",K10-L10) | N10: =IFERROR(L10/K10,"") | U10: =IF(T10="","",T10*(1-VacancyPct)) | W10: =IF(T10="","",T10*MgmtPct) | X10: =IF(T10="","",U10-Q10-R10-S10-V10-W10) | Y10: =IF(T10="","",(U10-R10-S10-V10-W10)*12) | Z10: =IFERROR(Y10/K10,"") | AA10: =IF(O10="","",IF(AND(O10-MarketRate30>=0.005,(1-N10)>=MinEquityPct),"Consider Refi",IF(O10-MarketRate30<0.005,"Rate already low","Build equity first")))
A11: 8 | M11: =IF(K11="","",K11-L11) | N11: =IFERROR(L11/K11,"") | U11: =IF(T11="","",T11*(1-VacancyPct)) | W11: =IF(T11="","",T11*MgmtPct) | X11: =IF(T11="","",U11-Q11-R11-S11-V11-W11) | Y11: =IF(T11="","",(U11-R11-S11-V11-W11)*12) | Z11: =IFERROR(Y11/K11,"") | AA11: =IF(O11="","",IF(AND(O11-MarketRate30>=0.005,(1-N11)>=MinEquityPct),"Consider Refi",IF(O11-MarketRate30<0.005,"Rate already low","Build equity first")))
A12: 9 | M12: =IF(K12="","",K12-L12) | N12: =IFERROR(L12/K12,"") | U12: =IF(T12="","",T12*(1-VacancyPct)) | W12: =IF(T12="","",T12*MgmtPct) | X12: =IF(T12="","",U12-Q12-R12-S12-V12-W12) | Y12: =IF(T12="","",(U12-R12-S12-V12-W12)*12) | Z12: =IFERROR(Y12/K12,"") | AA12: =IF(O12="","",IF(AND(O12-MarketRate30>=0.005,(1-N12)>=MinEquityPct),"Consider Refi",IF(O12-MarketRate30<0.005,"Rate already low","Build equity first")))
A13: 10 | M13: =IF(K13="","",K13-L13) | N13: =IFERROR(L13/K13,"") | U13: =IF(T13="","",T13*(1-VacancyPct)) | W13: =IF(T13="","",T13*MgmtPct) | X13: =IF(T13="","",U13-Q13-R13-S13-V13-W13) | Y13: =IF(T13="","",(U13-R13-S13-V13-W13)*12) | Z13: =IFERROR(Y13/K13,"") | AA13: =IF(O13="","",IF(AND(O13-MarketRate30>=0.005,(1-N13)>=MinEquityPct),"Consider Refi",IF(O13-MarketRate30<0.005,"Rate already low","Build equity first")))
A14: 11 | M14: =IF(K14="","",K14-L14) | N14: =IFERROR(L14/K14,"") | U14: =IF(T14="","",T14*(1-VacancyPct)) | W14: =IF(T14="","",T14*MgmtPct) | X14: =IF(T14="","",U14-Q14-R14-S14-V14-W14) | Y14: =IF(T14="","",(U14-R14-S14-V14-W14)*12) | Z14: =IFERROR(Y14/K14,"") | AA14: =IF(O14="","",IF(AND(O14-MarketRate30>=0.005,(1-N14)>=MinEquityPct),"Consider Refi",IF(O14-MarketRate30<0.005,"Rate already low","Build equity first")))
A15: 12 | M15: =IF(K15="","",K15-L15) | N15: =IFERROR(L15/K15,"") | U15: =IF(T15="","",T15*(1-VacancyPct)) | W15: =IF(T15="","",T15*MgmtPct) | X15: =IF(T15="","",U15-Q15-R15-S15-V15-W15) | Y15: =IF(T15="","",(U15-R15-S15-V15-W15)*12) | Z15: =IFERROR(Y15/K15,"") | AA15: =IF(O15="","",IF(AND(O15-MarketRate30>=0.005,(1-N15)>=MinEquityPct),"Consider Refi",IF(O15-MarketRate30<0.005,"Rate already low","Build equity first")))
A16: 13 | M16: =IF(K16="","",K16-L16) | N16: =IFERROR(L16/K16,"") | U16: =IF(T16="","",T16*(1-VacancyPct)) | W16: =IF(T16="","",T16*MgmtPct) | X16: =IF(T16="","",U16-Q16-R16-S16-V16-W16) | Y16: =IF(T16="","",(U16-R16-S16-V16-W16)*12) | Z16: =IFERROR(Y16/K16,"") | AA16: =IF(O16="","",IF(AND(O16-MarketRate30>=0.005,(1-N16)>=MinEquityPct),"Consider Refi",IF(O16-MarketRate30<0.005,"Rate already low","Build equity first")))
A17: 14 | M17: =IF(K17="","",K17-L17) | N17: =IFERROR(L17/K17,"") | U17: =IF(T17="","",T17*(1-VacancyPct)) | W17: =IF(T17="","",T17*MgmtPct) | X17: =IF(T17="","",U17-Q17-R17-S17-V17-W17) | Y17: =IF(T17="","",(U17-R17-S17-V17-W17)*12) | Z17: =IFERROR(Y17/K17,"") | AA17: =IF(O17="","",IF(AND(O17-MarketRate30>=0.005,(1-N17)>=MinEquityPct),"Consider Refi",IF(O17-MarketRate30<0.005,"Rate already low","Build equity first")))
A18: 15 | M18: =IF(K18="","",K18-L18) | N18: =IFERROR(L18/K18,"") | U18: =IF(T18="","",T18*(1-VacancyPct)) | W18: =IF(T18="","",T18*MgmtPct) | X18: =IF(T18="","",U18-Q18-R18-S18-V18-W18) | Y18: =IF(T18="","",(U18-R18-S18-V18-W18)*12) | Z18: =IFERROR(Y18/K18,"") | AA18: =IF(O18="","",IF(AND(O18-MarketRate30>=0.005,(1-N18)>=MinEquityPct),"Consider Refi",IF(O18-MarketRate30<0.005,"Rate already low","Build equity first")))
... A29: 26 | M29: =IF(K29="","",K29-L29) | N29: =IFERROR(L29/K29,"") | U29: =IF(T29="","",T29*(1-VacancyPct)) | W29: =IF(T29="","",T29*MgmtPct) | X29: =IF(T29="","",U29-Q29-R29-S29-V29-W29) | Y29: =IF(T29="","",(U29-R29-S29-V29-W29)*12) | Z29: =IFERROR(Y29/K29,"") | AA29: =IF(O29="","",IF(AND(O29-MarketRate30>=0.005,(1-N29)>=MinEquityPct),"Consider Refi",IF(O29-MarketRate30<0.005,"Rate already low","Build equity first")))
A31: PORTFOLIO TOTALS
A32: Total Value | B32: =SUMIF(K4:K29,">0") -> 675000
A33: Total Mortgage | B33: =SUMIF(L4:L29,">0") -> 425000
A34: Total Equity | B34: =B32-B33 -> 250000
A35: Avg LTV | B35: =IFERROR(B33/B32,0) -> 0.62962963
A36: Monthly Net Cash Flow | B36: =SUM(X4:X29) -> 443
A37: Annual NOI | B37: =SUM(Y4:Y29) -> 42396
A38: Portfolio Cap Rate | B38: =IFERROR(B37/B32,0) -> 0.062808889

Sheet Maintenance
A1: MAINTENANCE & IMPROVEMENT TRACKER
A3: Property | B3: System / Item | C3: Last Service / Install | D3: Lifespan (yrs) | E3: Next Due | F3: Status | G3: Cost Estimate | H3: Vendor | I3: Notes
A4: Sample 1 | B4: Roof | C4: 2010-08-01 | D4: 25 | E4: =IF(OR(C4="",D4=""),"",DATE(YEAR(C4)+D4,MONTH(C4),DAY(C4))) -> 49522 | F4: =IF(E4="","",IF(E4<TODAY(),"Overdue",IF(E4-TODAY()<=60,"Due within 60d","OK"))) -> OK | G4: 350
A5: Sample 1 | B5: HVAC | C5: 2018-05-15 | D5: 15 | E5: =IF(OR(C5="",D5=""),"",DATE(YEAR(C5)+D5,MONTH(C5),DAY(C5))) -> 48714 | F5: =IF(E5="","",IF(E5<TODAY(),"Overdue",IF(E5-TODAY()<=60,"Due within 60d","OK"))) -> OK | G5: 1500 | H5: Comfort Pros
A6: Sample 1 | B6: Water Heater | C6: 2021-01-10 | D6: 12 | E6: =IF(OR(C6="",D6=""),"",DATE(YEAR(C6)+D6,MONTH(C6),DAY(C6))) -> 48589 | F6: =IF(E6="","",IF(E6<TODAY(),"Overdue",IF(E6-TODAY()<=60,"Due within 60d","OK"))) -> OK | G6: 900
A7: Sample 2 | B7: Roof | C7: 2023-04-20 | D7: 25 | E7: =IF(OR(C7="",D7=""),"",DATE(YEAR(C7)+D7,MONTH(C7),DAY(C7))) -> 54168 | F7: =IF(E7="","",IF(E7<TODAY(),"Overdue",IF(E7-TODAY()<=60,"Due within 60d","OK"))) -> OK | G7: 0
A8: Sample 2 | B8: Furnace | C8: 2014-11-30 | D8: 20 | E8: =IF(OR(C8="",D8=""),"",DATE(YEAR(C8)+D8,MONTH(C8),DAY(C8))) -> 49278 | F8: =IF(E8="","",IF(E8<TODAY(),"Overdue",IF(E8-TODAY()<=60,"Due within 60d","OK"))) -> OK | G8: 2200
A9: Sample 3 | B9: Exterior Paint | C9: 2019-06-01 | D9: 8 | E9: =IF(OR(C9="",D9=""),"",DATE(YEAR(C9)+D9,MONTH(C9),DAY(C9))) -> 46539 | F9: =IF(E9="","",IF(E9<TODAY(),"Overdue",IF(E9-TODAY()<=60,"Due within 60d","OK"))) -> OK | G9: 4500 | H9: Local Painter
A10: Sample 3 | B10: Plumbing inspection | C10: 2024-09-15 | D10: 2 | E10: =IF(OR(C10="",D10=""),"",DATE(YEAR(C10)+D10,MONTH(C10),DAY(C10))) -> 46280 | F10: =IF(E10="","",IF(E10<TODAY(),"Overdue",IF(E10-TODAY()<=60,"Due within 60d","OK"))) -> OK | G10: 200 | H10: Annual
E11: =IF(OR(C11="",D11=""),"",DATE(YEAR(C11)+D11,MONTH(C11),DAY(C11))) | F11: =IF(E11="","",IF(E11<TODAY(),"Overdue",IF(E11-TODAY()<=60,"Due within 60d","OK")))
E12: =IF(OR(C12="",D12=""),"",DATE(YEAR(C12)+D12,MONTH(C12),DAY(C12))) | F12: =IF(E12="","",IF(E12<TODAY(),"Overdue",IF(E12-TODAY()<=60,"Due within 60d","OK")))
E13: =IF(OR(C13="",D13=""),"",DATE(YEAR(C13)+D13,MONTH(C13),DAY(C13))) | F13: =IF(E13="","",IF(E13<TODAY(),"Overdue",IF(E13-TODAY()<=60,"Due within 60d","OK")))
E14: =IF(OR(C14="",D14=""),"",DATE(YEAR(C14)+D14,MONTH(C14),DAY(C14))) | F14: =IF(E14="","",IF(E14<TODAY(),"Overdue",IF(E14-TODAY()<=60,"Due within 60d","OK")))
E15: =IF(OR(C15="",D15=""),"",DATE(YEAR(C15)+D15,MONTH(C15),DAY(C15))) | F15: =IF(E15="","",IF(E15<TODAY(),"Overdue",IF(E15-TODAY()<=60,"Due within 60d","OK")))
E16: =IF(OR(C16="",D16=""),"",DATE(YEAR(C16)+D16,MONTH(C16),DAY(C16))) | F16: =IF(E16="","",IF(E16<TODAY(),"Overdue",IF(E16-TODAY()<=60,"Due within 60d","OK")))
E17: =IF(OR(C17="",D17=""),"",DATE(YEAR(C17)+D17,MONTH(C17),DAY(C17))) | F17: =IF(E17="","",IF(E17<TODAY(),"Overdue",IF(E17-TODAY()<=60,"Due within 60d","OK")))
E18: =IF(OR(C18="",D18=""),"",DATE(YEAR(C18)+D18,MONTH(C18),DAY(C18))) | F18: =IF(E18="","",IF(E18<TODAY(),"Overdue",IF(E18-TODAY()<=60,"Due within 60d","OK")))
E19: =IF(OR(C19="",D19=""),"",DATE(YEAR(C19)+D19,MONTH(C19),DAY(C19))) | F19: =IF(E19="","",IF(E19<TODAY(),"Overdue",IF(E19-TODAY()<=60,"Due within 60d","OK")))
E20: =IF(OR(C20="",D20=""),"",DATE(YEAR(C20)+D20,MONTH(C20),DAY(C20))) | F20: =IF(E20="","",IF(E20<TODAY(),"Overdue",IF(E20-TODAY()<=60,"Due within 60d","OK")))
E21: =IF(OR(C21="",D21=""),"",DATE(YEAR(C21)+D21,MONTH(C21),DAY(C21))) | F21: =IF(E21="","",IF(E21<TODAY(),"Overdue",IF(E21-TODAY()<=60,"Due within 60d","OK")))
E22: =IF(OR(C22="",D22=""),"",DATE(YEAR(C22)+D22,MONTH(C22),DAY(C22))) | F22: =IF(E22="","",IF(E22<TODAY(),"Overdue",IF(E22-TODAY()<=60,"Due within 60d","OK")))
... E40: =IF(OR(C40="",D40=""),"",DATE(YEAR(C40)+D40,MONTH(C40),DAY(C40))) | F40: =IF(E40="","",IF(E40<TODAY(),"Overdue",IF(E40-TODAY()<=60,"Due within 60d","OK")))
A43: ALERTS SUMMARY
A44: Overdue items | B44: =COUNTIF(F4:F40,"Overdue") -> 0
A45: Due within 60 days | B45: =COUNTIF(F4:F40,"Due within 60d") -> 0
A46: Total upcoming cost (overdue + 60d) | B46: =SUMPRODUCT((F4:F40<>"OK")*(F4:F40<>"")*(G4:G40)) -> 0

Sheet Expenses
A1: EXPENSE TRACKER | J1: MONTHLY SUMMARY (current year)
A3: Date | B3: Property | C3: Category | D3: Vendor / Payee | E3: Description | F3: Amount | G3: Payment Method | H3: Receipt # | J3: Property | K3: MTD | L3: QTD | M3: YTD | N3: Last 12 mo
A4: 2026-04-01 | B4: Sample 1 | C4: Mortgage | D4: Chase | E4: April mortgage | F4: 1135 | G4: ACH | H4: Apr-MTG | J4: Sample 1 | K4: =SUMPRODUCT((B4:B79=J4)*(YEAR(A4:A79)=YEAR(TODAY()))*(MONTH(A4:A79)=MONTH(TODAY()))*F4:F79) -> 0 | L4: =SUMPRODUCT((B4:B79=J4)*(YEAR(A4:A79)=YEAR(TODAY()))*(INT((MONTH(A4:A79)-1)/3)=INT((MONTH(TODAY())-1)/3))*F4:F79) -> 1355 | M4: =SUMPRODUCT((B4:B79=J4)*(YEAR(A4:A79)=YEAR(TODAY()))*F4:F79) -> 1355 | N4: =SUMPRODUCT((B4:B79=J4)*(A4:A79>=EDATE(TODAY(),-12))*F4:F79) -> 1355
A5: 2026-04-01 | B5: Sample 2 | C5: Mortgage | D5: Wells Fargo | E5: April mortgage | F5: 525 | G5: ACH | H5: Apr-MTG2 | J5: Sample 2 | K5: =SUMPRODUCT((B4:B79=J5)*(YEAR(A4:A79)=YEAR(TODAY()))*(MONTH(A4:A79)=MONTH(TODAY()))*F4:F79) -> 0 | L5: =SUMPRODUCT((B4:B79=J5)*(YEAR(A4:A79)=YEAR(TODAY()))*(INT((MONTH(A4:A79)-1)/3)=INT((MONTH(TODAY())-1)/3))*F4:F79) -> 670 | M5: =SUMPRODUCT((B4:B79=J5)*(YEAR(A4:A79)=YEAR(TODAY()))*F4:F79) -> 670 | N5: =SUMPRODUCT((B4:B79=J5)*(A4:A79>=EDATE(TODAY(),-12))*F4:F79) -> 670
A6: 2026-04-05 | B6: Sample 1 | C6: Insurance | D6: State Farm | E6: Q2 premium | F6: 220 | G6: ACH | H6: INS-Q2 | J6: Sample 3 | K6: =SUMPRODUCT((B4:B79=J6)*(YEAR(A4:A79)=YEAR(TODAY()))*(MONTH(A4:A79)=MONTH(TODAY()))*F4:F79) -> 0 | L6: =SUMPRODUCT((B4:B79=J6)*(YEAR(A4:A79)=YEAR(TODAY()))*(INT((MONTH(A4:A79)-1)/3)=INT((MONTH(TODAY())-1)/3))*F4:F79) -> 1850 | M6: =SUMPRODUCT((B4:B79=J6)*(YEAR(A4:A79)=YEAR(TODAY()))*F4:F79) -> 1850 | N6: =SUMPRODUCT((B4:B79=J6)*(A4:A79>=EDATE(TODAY(),-12))*F4:F79) -> 1850
A7: 2026-04-12 | B7: Sample 2 | C7: Repairs | D7: Quick Plumbing | E7: Leaky faucet | F7: 145 | G7: Card | H7: RPR-118
A8: 2026-04-22 | B8: Sample 3 | C8: Property Tax | D8: Cuyahoga Cty | E8: 1H tax | F8: 1850 | G8: ACH | H8: TAX-1H
J10: TOTAL | K10: =SUM(K4:K9) -> 0 | L10: =SUM(L4:L9) -> 3875 | M10: =SUM(M4:M9) -> 3875 | N10: =SUM(N4:N9) -> 3875
J12: BY CATEGORY (YTD)
J14: Category | K14: YTD Total
J15: Mortgage | K15: =SUMPRODUCT((C4:C79=J15)*(YEAR(A4:A79)=YEAR(TODAY()))*F4:F79) -> 1660
J16: Property Tax | K16: =SUMPRODUCT((C4:C79=J16)*(YEAR(A4:A79)=YEAR(TODAY()))*F4:F79) -> 1850
J17: Insurance | K17: =SUMPRODUCT((C4:C79=J17)*(YEAR(A4:A79)=YEAR(TODAY()))*F4:F79) -> 220
J18: Utilities | K18: =SUMPRODUCT((C4:C79=J18)*(YEAR(A4:A79)=YEAR(TODAY()))*F4:F79) -> 0
J19: Repairs | K19: =SUMPRODUCT((C4:C79=J19)*(YEAR(A4:A79)=YEAR(TODAY()))*F4:F79) -> 145
J20: Capital Improvement | K20: =SUMPRODUCT((C4:C79=J20)*(YEAR(A4:A79)=YEAR(TODAY()))*F4:F79) -> 0
J21: Mgmt Fee | K21: =SUMPRODUCT((C4:C79=J21)*(YEAR(A4:A79)=YEAR(TODAY()))*F4:F79) -> 0
J22: HOA | K22: =SUMPRODUCT((C4:C79=J22)*(YEAR(A4:A79)=YEAR(TODAY()))*F4:F79) -> 0
J23: Travel | K23: =SUMPRODUCT((C4:C79=J23)*(YEAR(A4:A79)=YEAR(TODAY()))*F4:F79) -> 0
J24: Legal/Accounting | K24: =SUMPRODUCT((C4:C79=J24)*(YEAR(A4:A79)=YEAR(TODAY()))*F4:F79) -> 0
J25: Other | K25: =SUMPRODUCT((C4:C79=J25)*(YEAR(A4:A79)=YEAR(TODAY()))*F4:F79) -> 0

Sheet Refinance
A1: REFINANCE OPPORTUNITY ANALYZER
A3: Property | B3: Curr Balance | C3: Curr Rate | D3: Yrs Left | E3: Curr P&I | F3: Mkt Rate | G3: New Term | H3: New P&I | I3: Mo Savings | J3: Closing Cost | K3: Break-Even (mo) | L3: Decision
A4: =IF(Properties!B4="","",Properties!B4) -> Sample 1 | B4: =IF(Properties!L4="","",Properties!L4) -> 142000 | C4: =IF(Properties!O4="","",Properties!O4) -> 0.0625 | D4: 25 | E4: =IF(Properties!Q4="","",Properties!Q4) -> 1135 | F4: =MarketRate30 -> 0.0668 | G4: 30 | H4: =IF(OR(B4="",F4="",G4=""),"",PMT(F4/12,G4*12,-B4)) -> 914.41169 | I4: =IF(OR(E4="",H4=""),"",E4-H4) -> 220.58831 | J4: =IF(B4="","",B4*RefiCostPct) -> 3550 | K4: =IFERROR(IF(I4<=0,"No savings",J4/I4),"") -> 16.093328 | L4: =IF(I4="","",IF(C4-F4<0.005,"Skip - rate already low",IF(I4<=0,"Skip - no savings",IF(AND(I4>=RefiThreshold,K4<=24),"REFI NOW",IF(I4>=RefiThreshold,"Refi if staying long","Below threshold"))))) -> Skip - rate already low
A5: =IF(Properties!B5="","",Properties!B5) -> Sample 2 | B5: =IF(Properties!L5="","",Properties!L5) -> 78000 | C5: =IF(Properties!O5="","",Properties!O5) -> 0.0425 | D5: 25 | E5: =IF(Properties!Q5="","",Properties!Q5) -> 525 | F5: =MarketRate30 -> 0.0668 | G5: 30 | H5: =IF(OR(B5="",F5="",G5=""),"",PMT(F5/12,G5*12,-B5)) -> 502.28248 | I5: =IF(OR(E5="",H5=""),"",E5-H5) -> 22.717524 | J5: =IF(B5="","",B5*RefiCostPct) -> 1950 | K5: =IFERROR(IF(I5<=0,"No savings",J5/I5),"") -> 85.836818 | L5: =IF(I5="","",IF(C5-F5<0.005,"Skip - rate already low",IF(I5<=0,"Skip - no savings",IF(AND(I5>=RefiThreshold,K5<=24),"REFI NOW",IF(I5>=RefiThreshold,"Refi if staying long","Below threshold"))))) -> Skip - rate already low
A6: =IF(Properties!B6="","",Properties!B6) -> Sample 3 | B6: =IF(Properties!L6="","",Properties!L6) -> 205000 | C6: =IF(Properties!O6="","",Properties!O6) -> 0.075 | D6: 25 | E6: =IF(Properties!Q6="","",Properties!Q6) -> 1430 | F6: =MarketRate30 -> 0.0668 | G6: 30 | H6: =IF(OR(B6="",F6="",G6=""),"",PMT(F6/12,G6*12,-B6)) -> 1320.1014 | I6: =IF(OR(E6="",H6=""),"",E6-H6) -> 109.89862 | J6: =IF(B6="","",B6*RefiCostPct) -> 5125 | K6: =IFERROR(IF(I6<=0,"No savings",J6/I6),"") -> 46.633888 | L6: =IF(I6="","",IF(C6-F6<0.005,"Skip - rate already low",IF(I6<=0,"Skip - no savings",IF(AND(I6>=RefiThreshold,K6<=24),"REFI NOW",IF(I6>=RefiThreshold,"Refi if staying long","Below threshold"))))) -> Below threshold
A7: =IF(Properties!B7="","",Properties!B7) | B7: =IF(Properties!L7="","",Properties!L7) | C7: =IF(Properties!O7="","",Properties!O7) | E7: =IF(Properties!Q7="","",Properties!Q7) | F7: =MarketRate30 -> 0.0668 | H7: =IF(OR(B7="",F7="",G7=""),"",PMT(F7/12,G7*12,-B7)) | I7: =IF(OR(E7="",H7=""),"",E7-H7) | J7: =IF(B7="","",B7*RefiCostPct) | K7: =IFERROR(IF(I7<=0,"No savings",J7/I7),"") | L7: =IF(I7="","",IF(C7-F7<0.005,"Skip - rate already low",IF(I7<=0,"Skip - no savings",IF(AND(I7>=RefiThreshold,K7<=24),"REFI NOW",IF(I7>=RefiThreshold,"Refi if staying long","Below threshold")))))
A8: =IF(Properties!B8="","",Properties!B8) | B8: =IF(Properties!L8="","",Properties!L8) | C8: =IF(Properties!O8="","",Properties!O8) | E8: =IF(Properties!Q8="","",Properties!Q8) | F8: =MarketRate30 -> 0.0668 | H8: =IF(OR(B8="",F8="",G8=""),"",PMT(F8/12,G8*12,-B8)) | I8: =IF(OR(E8="",H8=""),"",E8-H8) | J8: =IF(B8="","",B8*RefiCostPct) | K8: =IFERROR(IF(I8<=0,"No savings",J8/I8),"") | L8: =IF(I8="","",IF(C8-F8<0.005,"Skip - rate already low",IF(I8<=0,"Skip - no savings",IF(AND(I8>=RefiThreshold,K8<=24),"REFI NOW",IF(I8>=RefiThreshold,"Refi if staying long","Below threshold")))))
A9: =IF(Properties!B9="","",Properties!B9) | B9: =IF(Properties!L9="","",Properties!L9) | C9: =IF(Properties!O9="","",Properties!O9) | E9: =IF(Properties!Q9="","",Properties!Q9) | F9: =MarketRate30 -> 0.0668 | H9: =IF(OR(B9="",F9="",G9=""),"",PMT(F9/12,G9*12,-B9)) | I9: =IF(OR(E9="",H9=""),"",E9-H9) | J9: =IF(B9="","",B9*RefiCostPct) | K9: =IFERROR(IF(I9<=0,"No savings",J9/I9),"") | L9: =IF(I9="","",IF(C9-F9<0.005,"Skip - rate already low",IF(I9<=0,"Skip - no savings",IF(AND(I9>=RefiThreshold,K9<=24),"REFI NOW",IF(I9>=RefiThreshold,"Refi if staying long","Below threshold")))))
A10: =IF(Properties!B10="","",Properties!B10) | B10: =IF(Properties!L10="","",Properties!L10) | C10: =IF(Properties!O10="","",Properties!O10) | E10: =IF(Properties!Q10="","",Properties!Q10) | F10: =MarketRate30 -> 0.0668 | H10: =IF(OR(B10="",F10="",G10=""),"",PMT(F10/12,G10*12,-B10)) | I10: =IF(OR(E10="",H10=""),"",E10-H10) | J10: =IF(B10="","",B10*RefiCostPct) | K10: =IFERROR(IF(I10<=0,"No savings",J10/I10),"") | L10: =IF(I10="","",IF(C10-F10<0.005,"Skip - rate already low",IF(I10<=0,"Skip - no savings",IF(AND(I10>=RefiThreshold,K10<=24),"REFI NOW",IF(I10>=RefiThreshold,"Refi if staying long","Below threshold")))))
A11: =IF(Properties!B11="","",Properties!B11) | B11: =IF(Properties!L11="","",Properties!L11) | C11: =IF(Properties!O11="","",Properties!O11) | E11: =IF(Properties!Q11="","",Properties!Q11) | F11: =MarketRate30 -> 0.0668 | H11: =IF(OR(B11="",F11="",G11=""),"",PMT(F11/12,G11*12,-B11)) | I11: =IF(OR(E11="",H11=""),"",E11-H11) | J11: =IF(B11="","",B11*RefiCostPct) | K11: =IFERROR(IF(I11<=0,"No savings",J11/I11),"") | L11: =IF(I11="","",IF(C11-F11<0.005,"Skip - rate already low",IF(I11<=0,"Skip - no savings",IF(AND(I11>=RefiThreshold,K11<=24),"REFI NOW",IF(I11>=RefiThreshold,"Refi if staying long","Below threshold")))))
A12: =IF(Properties!B12="","",Properties!B12) | B12: =IF(Properties!L12="","",Properties!L12) | C12: =IF(Properties!O12="","",Properties!O12) | E12: =IF(Properties!Q12="","",Properties!Q12) | F12: =MarketRate30 -> 0.0668 | H12: =IF(OR(B12="",F12="",G12=""),"",PMT(F12/12,G12*12,-B12)) | I12: =IF(OR(E12="",H12=""),"",E12-H12) | J12: =IF(B12="","",B12*RefiCostPct) | K12: =IFERROR(IF(I12<=0,"No savings",J12/I12),"") | L12: =IF(I12="","",IF(C12-F12<0.005,"Skip - rate already low",IF(I12<=0,"Skip - no savings",IF(AND(I12>=RefiThreshold,K12<=24),"REFI NOW",IF(I12>=RefiThreshold,"Refi if staying long","Below threshold")))))
A13: =IF(Properties!B13="","",Properties!B13) | B13: =IF(Properties!L13="","",Properties!L13) | C13: =IF(Properties!O13="","",Properties!O13) | E13: =IF(Properties!Q13="","",Properties!Q13) | F13: =MarketRate30 -> 0.0668 | H13: =IF(OR(B13="",F13="",G13=""),"",PMT(F13/12,G13*12,-B13)) | I13: =IF(OR(E13="",H13=""),"",E13-H13) | J13: =IF(B13="","",B13*RefiCostPct) | K13: =IFERROR(IF(I13<=0,"No savings",J13/I13),"") | L13: =IF(I13="","",IF(C13-F13<0.005,"Skip - rate already low",IF(I13<=0,"Skip - no savings",IF(AND(I13>=RefiThreshold,K13<=24),"REFI NOW",IF(I13>=RefiThreshold,"Refi if staying long","Below threshold")))))
A14: =IF(Properties!B14="","",Properties!B14) | B14: =IF(Properties!L14="","",Properties!L14) | C14: =IF(Properties!O14="","",Properties!O14) | E14: =IF(Properties!Q14="","",Properties!Q14) | F14: =MarketRate30 -> 0.0668 | H14: =IF(OR(B14="",F14="",G14=""),"",PMT(F14/12,G14*12,-B14)) | I14: =IF(OR(E14="",H14=""),"",E14-H14) | J14: =IF(B14="","",B14*RefiCostPct) | K14: =IFERROR(IF(I14<=0,"No savings",J14/I14),"") | L14: =IF(I14="","",IF(C14-F14<0.005,"Skip - rate already low",IF(I14<=0,"Skip - no savings",IF(AND(I14>=RefiThreshold,K14<=24),"REFI NOW",IF(I14>=RefiThreshold,"Refi if staying long","Below threshold")))))
A15: =IF(Properties!B15="","",Properties!B15) | B15: =IF(Properties!L15="","",Properties!L15) | C15: =IF(Properties!O15="","",Properties!O15) | E15: =IF(Properties!Q15="","",Properties!Q15) | F15: =MarketRate30 -> 0.0668 | H15: =IF(OR(B15="",F15="",G15=""),"",PMT(F15/12,G15*12,-B15)) | I15: =IF(OR(E15="",H15=""),"",E15-H15) | J15: =IF(B15="","",B15*RefiCostPct) | K15: =IFERROR(IF(I15<=0,"No savings",J15/I15),"") | L15: =IF(I15="","",IF(C15-F15<0.005,"Skip - rate already low",IF(I15<=0,"Skip - no savings",IF(AND(I15>=RefiThreshold,K15<=24),"REFI NOW",IF(I15>=RefiThreshold,"Refi if staying long","Below threshold")))))
A16: =IF(Properties!B16="","",Properties!B16) | B16: =IF(Properties!L16="","",Properties!L16) | C16: =IF(Properties!O16="","",Properties!O16) | E16: =IF(Properties!Q16="","",Properties!Q16) | F16: =MarketRate30 -> 0.0668 | H16: =IF(OR(B16="",F16="",G16=""),"",PMT(F16/12,G16*12,-B16)) | I16: =IF(OR(E16="",H16=""),"",E16-H16) | J16: =IF(B16="","",B16*RefiCostPct) | K16: =IFERROR(IF(I16<=0,"No savings",J16/I16),"") | L16: =IF(I16="","",IF(C16-F16<0.005,"Skip - rate already low",IF(I16<=0,"Skip - no savings",IF(AND(I16>=RefiThreshold,K16<=24),"REFI NOW",IF(I16>=RefiThreshold,"Refi if staying long","Below threshold")))))
A17: =IF(Properties!B17="","",Properties!B17) | B17: =IF(Properties!L17="","",Properties!L17) | C17: =IF(Properties!O17="","",Properties!O17) | E17: =IF(Properties!Q17="","",Properties!Q17) | F17: =MarketRate30 -> 0.0668 | H17: =IF(OR(B17="",F17="",G17=""),"",PMT(F17/12,G17*12,-B17)) | I17: =IF(OR(E17="",H17=""),"",E17-H17) | J17: =IF(B17="","",B17*RefiCostPct) | K17: =IFERROR(IF(I17<=0,"No savings",J17/I17),"") | L17: =IF(I17="","",IF(C17-F17<0.005,"Skip - rate already low",IF(I17<=0,"Skip - no savings",IF(AND(I17>=RefiThreshold,K17<=24),"REFI NOW",IF(I17>=RefiThreshold,"Refi if staying long","Below threshold")))))
A18: =IF(Properties!B18="","",Properties!B18) | B18: =IF(Properties!L18="","",Properties!L18) | C18: =IF(Properties!O18="","",Properties!O18) | E18: =IF(Properties!Q18="","",Properties!Q18) | F18: =MarketRate30 -> 0.0668 | H18: =IF(OR(B18="",F18="",G18=""),"",PMT(F18/12,G18*12,-B18)) | I18: =IF(OR(E18="",H18=""),"",E18-H18) | J18: =IF(B18="","",B18*RefiCostPct) | K18: =IFERROR(IF(I18<=0,"No savings",J18/I18),"") | L18: =IF(I18="","",IF(C18-F18<0.005,"Skip - rate already low",IF(I18<=0,"Skip - no savings",IF(AND(I18>=RefiThreshold,K18<=24),"REFI NOW",IF(I18>=RefiThreshold,"Refi if staying long","Below threshold")))))
... A29: =IF(Properties!B29="","",Properties!B29) | B29: =IF(Properties!L29="","",Properties!L29) | C29: =IF(Properties!O29="","",Properties!O29) | E29: =IF(Properties!Q29="","",Properties!Q29) | F29: =MarketRate30 -> 0.0668 | H29: =IF(OR(B29="",F29="",G29=""),"",PMT(F29/12,G29*12,-B29)) | I29: =IF(OR(E29="",H29=""),"",E29-H29) | J29: =IF(B29="","",B29*RefiCostPct) | K29: =IFERROR(IF(I29<=0,"No savings",J29/I29),"") | L29: =IF(I29="","",IF(C29-F29<0.005,"Skip - rate already low",IF(I29<=0,"Skip - no savings",IF(AND(I29>=RefiThreshold,K29<=24),"REFI NOW",IF(I29>=RefiThreshold,"Refi if staying long","Below threshold")))))
A32: HOW TO READ THIS
A33: • Mkt Rate pulls live from Settings sheet — update there once a month from Bankrate.
A34: • Closing cost defaults to 2.5% of new balance; tweak in Settings if your lender quotes differently.
A35: • Break-Even = closing cost ÷ monthly savings. Anything ≤ 24 months and you're staying ≥ 3-5 years is usually a yes.
A36: • Decision column considers both savings threshold ($150/mo default) AND break-even speed.
A37: • ALWAYS verify with a lender quote before pulling the trigger — Excel rates are national averages, not your offer.

Sheet Ohio Prospects
A1: OHIO ACQUISITION PIPELINE
A3: Status | B3: Address | C3: City | D3: Zip | E3: Type | F3: Bed/Bath | G3: Year | H3: List Price | I3: Est. ARV | J3: Est. Rent/mo | K3: Annual Tax | L3: Annual Ins | M3: Annual Mgmt+Repairs | N3: Down Pmt % | O3: Loan Rate | P3: Term | Q3: GRM | R3: 1% Rule | S3: Annual NOI | T3: Cap Rate | U3: Down $ | V3: Loan $ | W3: Mo P&I | X3: Annual CF | Y3: Cash-on-Cash | Z3: Score (100) | AA3: Notes
A4: Watching | B4: 100 Hot Lead Way | C4: Cleveland | D4: 44109 | E4: SFR | F4: 3/2 | G4: 1955 | H4: 95000 | I4: 130000 | J4: 1250 | K4: 1900 | L4: 850 | M4: 2200 | N4: 0.25 | O4: 0.075 | P4: 30 | Q4: =IFERROR(H4/(J4*12),"") -> 6.3333333 | R4: =IFERROR(J4/H4,"") -> 0.013157895 | S4: =IF(H4="","",J4*12*(1-VacancyPct)-K4-L4-M4) -> 8850 | T4: =IFERROR(S4/H4,"") -> 0.093157895 | U4: =IF(OR(H4="",N4=""),"",H4*N4) -> 23750 | V4: =IF(H4="","",H4-U4) -> 71250 | W4: =IF(OR(V4="",O4="",P4=""),"",PMT(O4/12,P4*12,-V4)) -> 498.19034 | X4: =IF(OR(S4="",W4=""),"",S4-W4*12) -> 2871.716 | Y4: =IFERROR(X4/U4,"") -> 0.12091436 | Z4: =IF(H4="","",ROUND( MIN(40,MAX(0, T4/TargetCapRate*40 )) +MIN(40,MAX(0, Y4/TargetCoC*40 )) +MIN(20,MAX(0, R4/0.01*20 )),0)) -> 100
A5: Touring | B5: 200 Equity Ln | C5: Dayton | D5: 45406 | E5: SFR | F5: 3/1.5 | G5: 1962 | H5: 119000 | I5: 155000 | J5: 1400 | K5: 1850 | L5: 950 | M5: 2400 | N5: 0.2 | O5: 0.075 | P5: 30 | Q5: =IFERROR(H5/(J5*12),"") -> 7.0833333 | R5: =IFERROR(J5/H5,"") -> 0.011764706 | S5: =IF(H5="","",J5*12*(1-VacancyPct)-K5-L5-M5) -> 10256 | T5: =IFERROR(S5/H5,"") -> 0.086184874 | U5: =IF(OR(H5="",N5=""),"",H5*N5) -> 23800 | V5: =IF(H5="","",H5-U5) -> 95200 | W5: =IF(OR(V5="",O5="",P5=""),"",PMT(O5/12,P5*12,-V5)) -> 665.65221 | X5: =IF(OR(S5="",W5=""),"",S5-W5*12) -> 2268.1735 | Y5: =IFERROR(X5/U5,"") -> 0.095301406 | Z5: =IF(H5="","",ROUND( MIN(40,MAX(0, T5/TargetCapRate*40 )) +MIN(40,MAX(0, Y5/TargetCoC*40 )) +MIN(20,MAX(0, R5/0.01*20 )),0)) -> 98
A6: Watching | B6: 300 Cap Rate Ct | C6: Toledo | D6: 43607 | E6: Duplex | F6: 2x2/1 | G6: 1968 | H6: 135000 | I6: 175000 | J6: 2050 | K6: 2100 | L6: 1100 | M6: 3300 | N6: 0.25 | O6: 0.075 | P6: 30 | Q6: =IFERROR(H6/(J6*12),"") -> 5.4878049 | R6: =IFERROR(J6/H6,"") -> 0.015185185 | S6: =IF(H6="","",J6*12*(1-VacancyPct)-K6-L6-M6) -> 16132 | T6: =IFERROR(S6/H6,"") -> 0.1194963 | U6: =IF(OR(H6="",N6=""),"",H6*N6) -> 33750 | V6: =IF(H6="","",H6-U6) -> 101250 | W6: =IF(OR(V6="",O6="",P6=""),"",PMT(O6/12,P6*12,-V6)) -> 707.95469 | X6: =IF(OR(S6="",W6=""),"",S6-W6*12) -> 7636.5437 | Y6: =IFERROR(X6/U6,"") -> 0.22626796 | Z6: =IF(H6="","",ROUND( MIN(40,MAX(0, T6/TargetCapRate*40 )) +MIN(40,MAX(0, Y6/TargetCoC*40 )) +MIN(20,MAX(0, R6/0.01*20 )),0)) -> 100
Q7: =IFERROR(H7/(J7*12),"") | R7: =IFERROR(J7/H7,"") | S7: =IF(H7="","",J7*12*(1-VacancyPct)-K7-L7-M7) | T7: =IFERROR(S7/H7,"") | U7: =IF(OR(H7="",N7=""),"",H7*N7) | V7: =IF(H7="","",H7-U7) | W7: =IF(OR(V7="",O7="",P7=""),"",PMT(O7/12,P7*12,-V7)) | X7: =IF(OR(S7="",W7=""),"",S7-W7*12) | Y7: =IFERROR(X7/U7,"") | Z7: =IF(H7="","",ROUND( MIN(40,MAX(0, T7/TargetCapRate*40 )) +MIN(40,MAX(0, Y7/TargetCoC*40 )) +MIN(20,MAX(0, R7/0.01*20 )),0))
Q8: =IFERROR(H8/(J8*12),"") | R8: =IFERROR(J8/H8,"") | S8: =IF(H8="","",J8*12*(1-VacancyPct)-K8-L8-M8) | T8: =IFERROR(S8/H8,"") | U8: =IF(OR(H8="",N8=""),"",H8*N8) | V8: =IF(H8="","",H8-U8) | W8: =IF(OR(V8="",O8="",P8=""),"",PMT(O8/12,P8*12,-V8)) | X8: =IF(OR(S8="",W8=""),"",S8-W8*12) | Y8: =IFERROR(X8/U8,"") | Z8: =IF(H8="","",ROUND( MIN(40,MAX(0, T8/TargetCapRate*40 )) +MIN(40,MAX(0, Y8/TargetCoC*40 )) +MIN(20,MAX(0, R8/0.01*20 )),0))
Q9: =IFERROR(H9/(J9*12),"") | R9: =IFERROR(J9/H9,"") | S9: =IF(H9="","",J9*12*(1-VacancyPct)-K9-L9-M9) | T9: =IFERROR(S9/H9,"") | U9: =IF(OR(H9="",N9=""),"",H9*N9) | V9: =IF(H9="","",H9-U9) | W9: =IF(OR(V9="",O9="",P9=""),"",PMT(O9/12,P9*12,-V9)) | X9: =IF(OR(S9="",W9=""),"",S9-W9*12) | Y9: =IFERROR(X9/U9,"") | Z9: =IF(H9="","",ROUND( MIN(40,MAX(0, T9/TargetCapRate*40 )) +MIN(40,MAX(0, Y9/TargetCoC*40 )) +MIN(20,MAX(0, R9/0.01*20 )),0))
Q10: =IFERROR(H10/(J10*12),"") | R10: =IFERROR(J10/H10,"") | S10: =IF(H10="","",J10*12*(1-VacancyPct)-K10-L10-M10) | T10: =IFERROR(S10/H10,"") | U10: =IF(OR(H10="",N10=""),"",H10*N10) | V10: =IF(H10="","",H10-U10) | W10: =IF(OR(V10="",O10="",P10=""),"",PMT(O10/12,P10*12,-V10)) | X10: =IF(OR(S10="",W10=""),"",S10-W10*12) | Y10: =IFERROR(X10/U10,"") | Z10: =IF(H10="","",ROUND( MIN(40,MAX(0, T10/TargetCapRate*40 )) +MIN(40,MAX(0, Y10/TargetCoC*40 )) +MIN(20,MAX(0, R10/0.01*20 )),0))
Q11: =IFERROR(H11/(J11*12),"") | R11: =IFERROR(J11/H11,"") | S11: =IF(H11="","",J11*12*(1-VacancyPct)-K11-L11-M11) | T11: =IFERROR(S11/H11,"") | U11: =IF(OR(H11="",N11=""),"",H11*N11) | V11: =IF(H11="","",H11-U11) | W11: =IF(OR(V11="",O11="",P11=""),"",PMT(O11/12,P11*12,-V11)) | X11: =IF(OR(S11="",W11=""),"",S11-W11*12) | Y11: =IFERROR(X11/U11,"") | Z11: =IF(H11="","",ROUND( MIN(40,MAX(0, T11/TargetCapRate*40 )) +MIN(40,MAX(0, Y11/TargetCoC*40 )) +MIN(20,MAX(0, R11/0.01*20 )),0))
Q12: =IFERROR(H12/(J12*12),"") | R12: =IFERROR(J12/H12,"") | S12: =IF(H12="","",J12*12*(1-VacancyPct)-K12-L12-M12) | T12: =IFERROR(S12/H12,"") | U12: =IF(OR(H12="",N12=""),"",H12*N12) | V12: =IF(H12="","",H12-U12) | W12: =IF(OR(V12="",O12="",P12=""),"",PMT(O12/12,P12*12,-V12)) | X12: =IF(OR(S12="",W12=""),"",S12-W12*12) | Y12: =IFERROR(X12/U12,"") | Z12: =IF(H12="","",ROUND( MIN(40,MAX(0, T12/TargetCapRate*40 )) +MIN(40,MAX(0, Y12/TargetCoC*40 )) +MIN(20,MAX(0, R12/0.01*20 )),0))
Q13: =IFERROR(H13/(J13*12),"") | R13: =IFERROR(J13/H13,"") | S13: =IF(H13="","",J13*12*(1-VacancyPct)-K13-L13-M13) | T13: =IFERROR(S13/H13,"") | U13: =IF(OR(H13="",N13=""),"",H13*N13) | V13: =IF(H13="","",H13-U13) | W13: =IF(OR(V13="",O13="",P13=""),"",PMT(O13/12,P13*12,-V13)) | X13: =IF(OR(S13="",W13=""),"",S13-W13*12) | Y13: =IFERROR(X13/U13,"") | Z13: =IF(H13="","",ROUND( MIN(40,MAX(0, T13/TargetCapRate*40 )) +MIN(40,MAX(0, Y13/TargetCoC*40 )) +MIN(20,MAX(0, R13/0.01*20 )),0))
Q14: =IFERROR(H14/(J14*12),"") | R14: =IFERROR(J14/H14,"") | S14: =IF(H14="","",J14*12*(1-VacancyPct)-K14-L14-M14) | T14: =IFERROR(S14/H14,"") | U14: =IF(OR(H14="",N14=""),"",H14*N14) | V14: =IF(H14="","",H14-U14) | W14: =IF(OR(V14="",O14="",P14=""),"",PMT(O14/12,P14*12,-V14)) | X14: =IF(OR(S14="",W14=""),"",S14-W14*12) | Y14: =IFERROR(X14/U14,"") | Z14: =IF(H14="","",ROUND( MIN(40,MAX(0, T14/TargetCapRate*40 )) +MIN(40,MAX(0, Y14/TargetCoC*40 )) +MIN(20,MAX(0, R14/0.01*20 )),0))
Q15: =IFERROR(H15/(J15*12),"") | R15: =IFERROR(J15/H15,"") | S15: =IF(H15="","",J15*12*(1-VacancyPct)-K15-L15-M15) | T15: =IFERROR(S15/H15,"") | U15: =IF(OR(H15="",N15=""),"",H15*N15) | V15: =IF(H15="","",H15-U15) | W15: =IF(OR(V15="",O15="",P15=""),"",PMT(O15/12,P15*12,-V15)) | X15: =IF(OR(S15="",W15=""),"",S15-W15*12) | Y15: =IFERROR(X15/U15,"") | Z15: =IF(H15="","",ROUND( MIN(40,MAX(0, T15/TargetCapRate*40 )) +MIN(40,MAX(0, Y15/TargetCoC*40 )) +MIN(20,MAX(0, R15/0.01*20 )),0))
Q16: =IFERROR(H16/(J16*12),"") | R16: =IFERROR(J16/H16,"") | S16: =IF(H16="","",J16*12*(1-VacancyPct)-K16-L16-M16) | T16: =IFERROR(S16/H16,"") | U16: =IF(OR(H16="",N16=""),"",H16*N16) | V16: =IF(H16="","",H16-U16) | W16: =IF(OR(V16="",O16="",P16=""),"",PMT(O16/12,P16*12,-V16)) | X16: =IF(OR(S16="",W16=""),"",S16-W16*12) | Y16: =IFERROR(X16/U16,"") | Z16: =IF(H16="","",ROUND( MIN(40,MAX(0, T16/TargetCapRate*40 )) +MIN(40,MAX(0, Y16/TargetCoC*40 )) +MIN(20,MAX(0, R16/0.01*20 )),0))
Q17: =IFERROR(H17/(J17*12),"") | R17: =IFERROR(J17/H17,"") | S17: =IF(H17="","",J17*12*(1-VacancyPct)-K17-L17-M17) | T17: =IFERROR(S17/H17,"") | U17: =IF(OR(H17="",N17=""),"",H17*N17) | V17: =IF(H17="","",H17-U17) | W17: =IF(OR(V17="",O17="",P17=""),"",PMT(O17/12,P17*12,-V17)) | X17: =IF(OR(S17="",W17=""),"",S17-W17*12) | Y17: =IFERROR(X17/U17,"") | Z17: =IF(H17="","",ROUND( MIN(40,MAX(0, T17/TargetCapRate*40 )) +MIN(40,MAX(0, Y17/TargetCoC*40 )) +MIN(20,MAX(0, R17/0.01*20 )),0))
Q18: =IFERROR(H18/(J18*12),"") | R18: =IFERROR(J18/H18,"") | S18: =IF(H18="","",J18*12*(1-VacancyPct)-K18-L18-M18) | T18: =IFERROR(S18/H18,"") | U18: =IF(OR(H18="",N18=""),"",H18*N18) | V18: =IF(H18="","",H18-U18) | W18: =IF(OR(V18="",O18="",P18=""),"",PMT(O18/12,P18*12,-V18)) | X18: =IF(OR(S18="",W18=""),"",S18-W18*12) | Y18: =IFERROR(X18/U18,"") | Z18: =IF(H18="","",ROUND( MIN(40,MAX(0, T18/TargetCapRate*40 )) +MIN(40,MAX(0, Y18/TargetCoC*40 )) +MIN(20,MAX(0, R18/0.01*20 )),0))
... Q29: =IFERROR(H29/(J29*12),"") | R29: =IFERROR(J29/H29,"") | S29: =IF(H29="","",J29*12*(1-VacancyPct)-K29-L29-M29) | T29: =IFERROR(S29/H29,"") | U29: =IF(OR(H29="",N29=""),"",H29*N29) | V29: =IF(H29="","",H29-U29) | W29: =IF(OR(V29="",O29="",P29=""),"",PMT(O29/12,P29*12,-V29)) | X29: =IF(OR(S29="",W29=""),"",S29-W29*12) | Y29: =IFERROR(X29/U29,"") | Z29: =IF(H29="","",ROUND( MIN(40,MAX(0, T29/TargetCapRate*40 )) +MIN(40,MAX(0, Y29/TargetCoC*40 )) +MIN(20,MAX(0, R29/0.01*20 )),0))
A32: SCORING METHODOLOGY
A33: Score = 40 pts (cap rate vs target) + 40 pts (cash-on-cash vs target) + 20 pts (1% rule).
A34: 85+ = strong buy candidate · 70-84 = analyze deeper · <70 = pass or negotiate harder.
A35: Targets are set on the Settings sheet. Adjust to your own underwriting.

Sheet Ohio Market
B2: OHIO MARKET REFERENCE
B3: Snapshot of top Ohio markets and current refi context (May 2026). Refresh quarterly.
B5: TOP OHIO INVESTMENT MARKETS
B7: City | C7: Median Price | D7: Rent-to-Yield | E7: 2026 Forecast | F7: Cap Rate Range | G7: Investment Thesis
B8: Cincinnati | C8: 279000 | D8: 0.085 | E8: Strong demand | F8: 7-9% | G8: RentCafe #1 hottest rental market into 2026; 81% YoY apartment demand jump. Strong multifamily play.
B9: Columbus | C9: 285000 | D9: 0.09 | E9: +5-7% | F9: 8-10% | G9: $20B Intel semiconductor project drives jobs, talent, housing demand. Balanced yield + low vacancy.
B10: Cleveland | C10: 150000 | D10: 0.113 | E10: Stable | F10: 10-13% | G10: Highest rent-to-yield ratio (~11.3%). Best cash flow city in the state. Watch neighborhood-specific risk.
B11: Toledo | C11: 150000 | D11: 0.095 | E11: +13.1% | F11: 9-12% | G11: Projected to lead Ohio in price growth (13.1%). Affordability + demand. Underpriced market.
B12: Dayton | C12: 133000 | D12: 0.105 | E12: Stable | F12: 9-12% | G12: "Cash Flow Capital" — most affordable entry in Ohio. Strong 1% rule territory.
B16: MORTGAGE RATE CONTEXT (May 3, 2026)
B18: 30-yr fixed refi (Bankrate national avg)
B19: 30-yr fixed refi (Zillow)
B20: April 2026 low (April 18)
B21: Q2 2026 forecast (MBA / Fannie Mae)
B22: 15-yr fixed refi (approx)
B24: TREND: Started April at ~6.30%, dipped to 6.02% on Apr 18, climbed back to 6.20%, now 6.62-6.68%. Inflation + global tensions keeping rates elevated. Rates fluctuate daily — quote multiple lenders.
B26: SOURCES
B28: • Norada Real Estate — Best Cities in Ohio to Invest in Real Estate in 2026
B29: • Norada Real Estate — Mortgage Rates Today, May 3, 2026
B30: • Bankrate — Current Refinance Rates (refreshed daily)
B31: • RentCafe — 2026 Hottest Rental Markets
B32: • Easy Street Capital — Top 5 Best Places to Invest in Ohio Real Estate in 2026

Sheet Settings
B2: GLOBAL ASSUMPTIONS
B4: Assumption | C4: Value | D4: Notes
B5: Current 30-yr market mortgage rate | C5: 0.0668 | D5: As of May 3, 2026 — Bankrate national average. Update monthly.
B6: Current 15-yr market mortgage rate | C6: 0.0595 | D6: Approx. Update from Bankrate or your lender.
B7: Refi closing cost (% of loan) | C7: 0.025 | D7: Typical 2-3% of new loan amount.
B8: Target cap rate (Ohio) | C8: 0.085 | D8: Ohio cash-flow markets often 8-12%.
B9: Target cash-on-cash return | C9: 0.1 | D9: 10%+ is strong for buy-and-hold.
B10: Min equity for refi (%) | C10: 0.2 | D10: Most lenders require 20% equity / 80% LTV.
B11: Refi savings threshold ($/mo) | C11: 150 | D11: Don't refi unless monthly savings clear this hurdle.
B12: Vacancy assumption (%) | C12: 0.08 | D12: Typical SFR underwriting.
B13: Property mgmt fee (% of rent) | C13: 0.08 | D13: If self-managing, set to 0%.

Sheet _Lists
A1: Mortgage | B1: Sample 1
A2: Property Tax | B2: Sample 2
A3: Insurance | B3: Sample 3
A4: Utilities
A5: Repairs
A6: Capital Improvement
A7: Mgmt Fee
A8: HOA
A9: Travel
A10: Watching
A11: Touring
A12: Offer
A13: Won
A14: Lost
